pynavlib/__init__.py
pynavlib/_pynavlib.cpython-311-darwin.so
pynavlib/pynavlib_interface.py
pynavlib-0.9.4.dist-info/LICENSE
pynavlib-0.9.4.dist-info/METADATA
pynavlib-0.9.4.dist-info/WHEEL
pynavlib-0.9.4.dist-info/top_level.txt
pynavlib-0.9.4.dist-info/RECORD
