Metadata-Version: 2.2
Name: pynavlib
Version: 0.9.4
Summary: Python binding for the 3Dconnexion's Navigation Library.
Author: 3Dconnexion
License: Copyright 2024 3Dconnexion
Project-URL: Documentation, https://github.com/3Dconnexion/pynavlib
Project-URL: Changes, https://github.com/3Dconnexion/pynavlib/blob/main/Changes.md
Project-URL: 3Dconnexion, https://3Dconnexion.com
Classifier: Development Status :: 3 - Alpha
Classifier: Intended Audience :: Developers
Classifier: Topic :: Software Development :: Libraries :: Python Modules
Classifier: License :: OSI Approved :: MIT License
Classifier: Operating System :: Microsoft :: Windows
Classifier: Operating System :: MacOS
Requires-Python: <3.14,>=3.10
License-File: LICENSE
